buildblock/__init__.py
buildblock/apps/__init__.py
buildblock/apps/access_control.py
buildblock/apps/administrator/__init__.py
buildblock/apps/administrator/admin.py
buildblock/apps/administrator/apps.py
buildblock/apps/administrator/forms.py
buildblock/apps/administrator/migrations/0001_initial.py
buildblock/apps/administrator/migrations/__init__.py
buildblock/apps/administrator/models.py
buildblock/apps/administrator/urls.py
buildblock/apps/administrator/views/__init__.py
buildblock/apps/administrator/views/base.py
buildblock/apps/administrator/views/email.py
buildblock/apps/administrator/views/investment.py
buildblock/apps/administrator/views/landing.py
buildblock/apps/administrator/views/lease.py
buildblock/apps/administrator/views/product.py
buildblock/apps/administrator/views/property.py
buildblock/apps/administrator/views/user.py
buildblock/apps/construction/__init__.py
buildblock/apps/construction/admin.py
buildblock/apps/construction/apps.py
buildblock/apps/construction/contexts.py
buildblock/apps/construction/forms.py
buildblock/apps/construction/migrations/0001_initial.py
buildblock/apps/construction/migrations/0002_auto_20200522_1417.py
buildblock/apps/construction/migrations/0003_auto_20200602_1132.py
buildblock/apps/construction/migrations/0004_constructionexpense_item.py
buildblock/apps/construction/migrations/0005_constructionpersonnelexpense_is_paid.py
buildblock/apps/construction/migrations/0006_auto_20200616_1448.py
buildblock/apps/construction/migrations/0007_historicalconstruction_historicalconstructionexpense_historicalconstructionpersonnelexpense_historic.py
buildblock/apps/construction/migrations/0008_auto_20200703_1102.py
buildblock/apps/construction/migrations/0009_auto_20200915_1206.py
buildblock/apps/construction/migrations/0010_auto_20200924_1203.py
buildblock/apps/construction/migrations/0011_auto_20200924_1543.py
buildblock/apps/construction/migrations/__init__.py
buildblock/apps/construction/models.py
buildblock-2.0.0.dist-info/LICENSE
buildblock-2.0.0.dist-info/WHEEL
buildblock-2.0.0.dist-info/METADATA
buildblock-2.0.0.dist-info/RECORD
