Metadata-Version: 2.1
Name: buildblock
Version: 2.0.0
Summary: Initialize poetry
Author: coloryourlife
Author-email: 95chris0319@gmail.com
Requires-Python: >=3.9,<4.0
Classifier: Programming Language :: Python :: 3
Classifier: Programming Language :: Python :: 3.9
Requires-Dist: Pillow (>=8.3.0,<9.0.0)
Requires-Dist: argon2-cffi (>=20.1.0,<21.0.0)
Requires-Dist: aws-encryption-sdk (>=3.0.0,<4.0.0)
Requires-Dist: blockscore (>=4.1.0,<5.0.0)
Requires-Dist: boto3 (>=1.17.104,<2.0.0)
Requires-Dist: coreapi (>=2.3.3,<3.0.0)
Requires-Dist: django (>=3.2.4,<4.0.0)
Requires-Dist: django-allauth (>=0.44.0,<0.45.0)
Requires-Dist: django-background-tasks (>=1.2.5,<2.0.0)
Requires-Dist: django-better-admin-arrayfield (>=1.4.2,<2.0.0)
Requires-Dist: django-ckeditor (>=6.1.0,<7.0.0)
Requires-Dist: django-cors-headers (>=3.7.0,<4.0.0)
Requires-Dist: django-crispy-forms (>=1.12.0,<2.0.0)
Requires-Dist: django-environ (>=0.4.5,<0.5.0)
Requires-Dist: django-guardian (>=2.4.0,<3.0.0)
Requires-Dist: django-hitcount (>=1.3.3,<2.0.0)
Requires-Dist: django-mathfilters (>=1.0.0,<2.0.0)
Requires-Dist: django-model-utils (>=4.1.1,<5.0.0)
Requires-Dist: django-modeltranslation (>=0.17.3,<0.18.0)
Requires-Dist: django-private-storage (>=2.3.0,<3.0.0)
Requires-Dist: django-redis (>=4.1.0,<5.0.0)
Requires-Dist: django-simple-history (>=3.0.0,<4.0.0)
Requires-Dist: django-widget-tweaks (>=1.4.8,<2.0.0)
Requires-Dist: djangorestframework (>=3.12.4,<4.0.0)
Requires-Dist: docusign-esign (>=3.10.0,<4.0.0)
Requires-Dist: easy-thumbnails (>=2.7.1,<3.0.0)
Requires-Dist: googlemaps (>=4.4.5,<5.0.0)
Requires-Dist: langdetect (>=1.0.9,<2.0.0)
Requires-Dist: marshmallow (>=3.12.1,<4.0.0)
Requires-Dist: paypal-checkout-serversdk (>=1.0.1,<2.0.0)
Requires-Dist: psycopg2 (>=2.9.1,<3.0.0)
Requires-Dist: psycopg2-binary (>=2.9.1,<3.0.0)
Requires-Dist: python-slugify (>=5.0.2,<6.0.0)
Requires-Dist: redis (>=3.5.3,<4.0.0)
Requires-Dist: stripe (>=2.58.0,<3.0.0)
Requires-Dist: us (>=2.0.2,<3.0.0)
Requires-Dist: web3 (>=5.20.1,<6.0.0)
